openmas/__init__.py
openmas/agent/__init__.py
openmas/agent/base.py
openmas/agent/base.py.bak
openmas/agent/bdi.py
openmas/agent/mcp.py
openmas/agent/mcp_client.py
openmas/agent/mcp_prompt.py
openmas/agent/mcp_server.py
openmas/agent/spade_bdi_agent.py
openmas/assets/__init__.py
openmas/assets/config.py
openmas/assets/downloaders.py
openmas/assets/exceptions.py
openmas/assets/manager.py
openmas/assets/utils.py
openmas/cli/__init__.py
openmas/cli/__main__.py
openmas/cli/assets.py
openmas/cli/deploy.py
openmas/cli/main.py
openmas/cli/main.py.bak
openmas/cli/prompts.py
openmas/cli/run.py
openmas/cli/utils.py
openmas/cli/validate.py
openmas/communication/README.md
openmas/communication/__init__.py
openmas/communication/base.py
openmas/communication/grpc/README.md
openmas/communication/grpc/__init__.py
openmas/communication/grpc/base.py
openmas/communication/grpc/communicator.py
openmas/communication/grpc/generate_proto.py
openmas/communication/grpc/openmas.proto
openmas/communication/grpc/openmas_pb2.py
openmas/communication/grpc/openmas_pb2_grpc.py
openmas/communication/http.py
openmas/communication/mcp/README.md
openmas/communication/mcp/__init__.py
openmas/communication/mcp/sse_communicator.py
openmas/communication/mcp/stdio_communicator.py
openmas/communication/mqtt/__init__.py
openmas/communication/mqtt/communicator.py
openmas/config.py
openmas/deployment/__init__.py
openmas/deployment/cli.py
openmas/deployment/discovery.py
openmas/deployment/generators.py
openmas/deployment/metadata.py
openmas/deployment/orchestration.py
openmas/exceptions.py
openmas/integrations/__init__.py
openmas/integrations/llm.py
openmas/logging.py
openmas/patterns/__init__.py
openmas/patterns/chaining.py
openmas/patterns/orchestrator.py
openmas/prompt/__init__.py
openmas/prompt/base.py
openmas/prompt/mcp.py
openmas/sampling/__init__.py
openmas/sampling/base.py
openmas/sampling/providers/__init__.py
openmas/sampling/providers/mcp.py
openmas/testing/__init__.py
openmas/testing/harness.py
openmas-0.2.2.dist-info/LICENSE
openmas-0.2.2.dist-info/METADATA
openmas-0.2.2.dist-info/WHEEL
openmas-0.2.2.dist-info/entry_points.txt
openmas-0.2.2.dist-info/RECORD
