Metadata-Version: 2.3
Name: openmas
Version: 0.2.2
Summary: OpenMAS: Easily Build Smart Multi-Agent Systems
License: MIT
Keywords: multi-agent-systems,mas,agent,ai,mcp,model-context-protocol,framework
Author: Wilson Urdaneta
Author-email: wilson.urdaneta@gmail.com
Requires-Python: >=3.10,<4.0
Classifier: Development Status :: 4 - Beta
Classifier: Intended Audience :: Developers
Classifier: License :: OSI Approved :: MIT License
Classifier: Operating System :: OS Independent
Classifier: Programming Language :: Python :: 3
Classifier: Programming Language :: Python :: 3.10
Classifier: Programming Language :: Python :: 3.11
Classifier: Programming Language :: Python :: 3.12
Classifier: Programming Language :: Python :: 3.13
Classifier: Topic :: Scientific/Engineering :: Artificial Intelligence
Classifier: Topic :: Software Development :: Libraries :: Python Modules
Provides-Extra: all
Provides-Extra: grpc
Provides-Extra: mcp
Provides-Extra: mqtt
Provides-Extra: tqdm
Requires-Dist: aiohttp (>=3.11.18,<4.0.0)
Requires-Dist: fastapi (>=0.115.12,<0.116.0)
Requires-Dist: filelock (>=3.18.0,<4.0.0)
Requires-Dist: grpcio (>=1.71.0,<2.0.0) ; extra == "grpc" or extra == "all"
Requires-Dist: grpcio-tools (>=1.71.0,<2.0.0) ; extra == "grpc" or extra == "all"
Requires-Dist: httpx (>=0.25.0)
Requires-Dist: httpx-sse (>=0.4.0,<0.5.0)
Requires-Dist: mcp (>=1.7.1) ; extra == "mcp" or extra == "all"
Requires-Dist: paho-mqtt (>=1.6.1,<2.0.0) ; extra == "mqtt" or extra == "all"
Requires-Dist: protobuf (>=5.26.1,<6.0.0) ; extra == "grpc" or extra == "all"
Requires-Dist: pydantic (>=2.5.0,<3.0.0)
Requires-Dist: python-chess (>=1.999,<2.0)
Requires-Dist: python-dotenv (>=1.1.0,<2.0.0)
Requires-Dist: pyyaml (>=6.0.1,<7.0.0)
Requires-Dist: structlog (>=23.2.0,<24.0.0)
Requires-Dist: tomli (>=2.2.1,<3.0.0)
Requires-Dist: tqdm (>=4.66.1,<5.0.0) ; extra == "tqdm" or extra == "all"
Requires-Dist: typer (>=0.15.2,<0.16.0)
Requires-Dist: uvicorn (>=0.34.2,<0.35.0)
Project-URL: Documentation, https://docs.openmas.ai
Project-URL: Homepage, https://openmas.ai
Project-URL: Repository, https://github.com/openmas-ai/openmas
